qin/__init__.py
qin/ai.py
qin/file.py
qin/git.py
qin/main.py
qin/media.py
qin/common/__init__.py
qin/common/ai.py
qin/common/file.py
qin/common/logger.py
qin/config/__init__.py
qin/config/base.py
qin/config/config.py
qin-0.1.3.dist-info/LICENSE
qin-0.1.3.dist-info/METADATA
qin-0.1.3.dist-info/WHEEL
qin-0.1.3.dist-info/entry_points.txt
qin-0.1.3.dist-info/top_level.txt
qin-0.1.3.dist-info/RECORD
