Metadata-Version: 2.1
Name: qin
Version: 0.1.3
Summary: Interesting toolset
Home-page: https://github.com/Alndaly/qin-cli
Author: Kinda Hall
Author-email: 1142704468@qq.com
Maintainer: Kinda Hall
Maintainer-email: 1142704468@qq.com
License: Copyright (c) 2023 Kinda Hall
Keywords: pip,tools
Platform: macOS
Requires-Python: >=3.10
License-File: LICENSE
Requires-Dist: typer
Requires-Dist: ffmpeg-python
Requires-Dist: oss2
Requires-Dist: gradio
Requires-Dist: yt-dlp
Requires-Dist: fastapi
Requires-Dist: moviepy
Requires-Dist: httpx
Requires-Dist: urllib3 >=2.0
